setup.py
dsnd_azeem_dist/Binomialdistribution.py
dsnd_azeem_dist/Gaussiandistribution.py
dsnd_azeem_dist/Generaldistribution.py
dsnd_azeem_dist/__init__.py
dsnd_azeem_dist.egg-info/PKG-INFO
dsnd_azeem_dist.egg-info/SOURCES.txt
dsnd_azeem_dist.egg-info/dependency_links.txt
dsnd_azeem_dist.egg-info/not-zip-safe
dsnd_azeem_dist.egg-info/top_level.txt